odoo/addons/account_commission/README.rst
odoo/addons/account_commission/__init__.py
odoo/addons/account_commission/__manifest__.py
odoo/addons/account_commission/data/menuitem_data.xml
odoo/addons/account_commission/i18n/account_commission.pot
odoo/addons/account_commission/i18n/es.po
odoo/addons/account_commission/i18n/hr.po
odoo/addons/account_commission/i18n/it.po
odoo/addons/account_commission/i18n/ja.po
odoo/addons/account_commission/i18n/pt.po
odoo/addons/account_commission/i18n/pt_BR.po
odoo/addons/account_commission/i18n/tr.po
odoo/addons/account_commission/models/__init__.py
odoo/addons/account_commission/models/account_move.py
odoo/addons/account_commission/models/commission.py
odoo/addons/account_commission/models/commission_settlement.py
odoo/addons/account_commission/readme/CONFIGURE.md
odoo/addons/account_commission/readme/CONTRIBUTORS.md
odoo/addons/account_commission/readme/DESCRIPTION.md
odoo/addons/account_commission/readme/USAGE.md
odoo/addons/account_commission/report/__init__.py
odoo/addons/account_commission/report/commission_analysis.py
odoo/addons/account_commission/report/commission_analysis_view.xml
odoo/addons/account_commission/security/account_commission_security.xml
odoo/addons/account_commission/security/ir.model.access.csv
odoo/addons/account_commission/static/description/icon.png
odoo/addons/account_commission/static/description/icon.svg
odoo/addons/account_commission/static/description/index.html
odoo/addons/account_commission/tests/__init__.py
odoo/addons/account_commission/tests/test_account_commission.py
odoo/addons/account_commission/views/account_move_views.xml
odoo/addons/account_commission/views/commission_settlement_views.xml
odoo/addons/account_commission/views/commission_views.xml
odoo/addons/account_commission/views/grouped_report_settlement_templates.xml
odoo/addons/account_commission/views/report_settlement_templates.xml
odoo/addons/account_commission/wizards/__init__.py
odoo_addon_account_commission-17.0.1.0.1.2.dist-info/METADATA
odoo_addon_account_commission-17.0.1.0.1.2.dist-info/WHEEL
odoo_addon_account_commission-17.0.1.0.1.2.dist-info/top_level.txt
odoo_addon_account_commission-17.0.1.0.1.2.dist-info/RECORD
